{"is_source_file": true, "format": "JavaScript/React JSX", "description": "React component for the Housekeeping Dashboard, displaying room statuses, filters, and assigned tasks.", "external_files": ["../hooks/useRealtimeRooms", "../components/RoomCard", "../services/api"], "external_methods": ["useRealtimeRooms()", "apiFetch()"], "published": [], "classes": [], "methods": [{"name": "HousekeepingDashboard()", "description": "Main React functional component rendering the housekeeping dashboard UI.", "scope": "", "scopeKind": ""}], "calls": ["useRealtimeRooms()", "apiFetch(\"/tasks/assigned\")", "setAssigned()", "rooms.filter()", "rooms.reduce()", "setFilter()", "setFilter()", "rooms.map()", "assigned.map()", "new Date(t.due_at).toLocaleString()"], "search-terms": ["HousekeepingDashboard.jsx", "useRealtimeRooms", "RoomCard", "apiFetch", "tasks/assigned", "room status filters", "assigned tasks display", "React hooks usage", "room status counts"], "state": 2, "file_id": 25, "knowledge_revision": 81, "git_revision": "406ddfb1f963654ac5b753c25579cd416f61b887", "revision_history": [{"55": ""}, {"81": "406ddfb1f963654ac5b753c25579cd416f61b887"}], "ctags": [{"_type": "tag", "name": "HousekeepingDashboard", "path": "/home/kavia/workspace/code-generation/hotel-operations-management-platform-163446-163455/smartroomops_frontend/src/pages/HousekeepingDashboard.jsx", "pattern": "/^export default function HousekeepingDashboard() {$/", "language": "JavaScript", "kind": "function", "signature": "()"}], "hash": "46ebd2da1fff66dbaee75976fee5e9b1", "format-version": 4, "code-base-name": "smartroomops_frontend", "filename": "smartroomops_frontend/src/pages/HousekeepingDashboard.jsx"}